{
  "$schema": "https://docs.openclaw.ai/skills/schema.json",
  "id": "bottleneck-identification",
  "name": "Bottleneck Identification",
  "description": "Identifies and resolves blockages in creative, production, and campaign workflows to keep projects moving and deadlines on track.",
  "category": "operations",
  "difficulty": "intermediate",
  "freedom": "medium",
  "prompts": {
    "en": {
      "trigger": "Use when a project or workflow is behind schedule, tasks are piling up, or the team is blocked — to identify the specific bottleneck causing the slowdown.",
      "context": "You are an operations analyst who systematically diagnoses workflow blockages and prescribes targeted fixes to restore flow and meet deadlines.",
      "instructions": "## Bottleneck Identification Workflow\n\n- [ ] 1. Map the process: Lay out the full workflow from brief to delivery\n- [ ] 2. Measure throughput: Identify which stages take longest and have most work-in-progress\n- [ ] 3. Find the constraint: Identify the single limiting factor (the bottleneck)\n- [ ] 4. Diagnose cause: Is it capacity, dependency, decision-making, or rework?\n- [ ] 5. Prioritize fixes: Short-term workaround vs. long-term structural fix\n- [ ] 6. Implement: Address the bottleneck\n- [ ] 7. Monitor: Ensure throughput improves\n\n## Key Inputs\n- Process: {{process_name}}\n- Current blockers: {{current_blockers}}\n- Timeline impact: {{timeline_impact}}",
      "output_template": "## Bottleneck Analysis: {{process_name}}\n\n### Process Map\n| Stage | Duration | Work in progress | Capacity |\n|-------|----------|-----------------|----------|\n| | | | |\n\n### Bottleneck Identified\n**Stage:**\n**Type:** Capacity / Dependency / Decision / Rework\n**Root cause:**\n**Impact:**\n\n### Fix Recommendations\n| Fix | Type | Effort | Impact | Priority |\n|-----|------|--------|--------|----------|\n| | | | | |\n\n### Short-Term Workaround\n| Action | Owner | By when |\n|--------|-------|---------|\n| | | |\n\n### Long-Term Structural Fix\n| Action | Owner | By when |\n|--------|-------|---------|\n| | | |\n\n### Expected Outcome\n| Metric | Before | After |\n|--------|--------|-------|\n| | | |"
    }
  },
  "variables": [
    {
      "name": "process_name",
      "type": "string",
      "required": true,
      "description": "Name of the workflow or process"
    },
    {
      "name": "current_blockers",
      "type": "string",
      "required": false,
      "description": "Description of current blockers or delays"
    },
    {
      "name": "timeline_impact",
      "type": "string",
      "required": false,
      "description": "How the bottleneck is affecting the timeline"
    }
  ],
  "workflow": {
    "steps": [
      {
        "step": 1,
        "name": "Process Mapping",
        "action": "Document the full workflow",
        "verify": "All stages are identified and sequenced"
      },
      {
        "step": 2,
        "name": "Constraint Identification",
        "action": "Find the single limiting factor",
        "verify": "Bottleneck is clearly identified"
      },
      {
        "step": 3,
        "name": "Root Cause Diagnosis",
        "action": "Understand why the bottleneck exists",
        "verify": "Cause is specific and actionable"
      },
      {
        "step": 4,
        "name": "Fix Prioritization",
        "action": "Short-term workaround vs. long-term fix",
        "verify": "Both timeframes are addressed"
      },
      {
        "step": 5,
        "name": "Implementation",
        "action": "Execute the fixes",
        "verify": "Throughput improves"
      }
    ]
  },
  "examples": [
    {
      "input": "Campaign creative is behind schedule. The brief-to-design handoff takes 3 days on average. Design is a 5-day task. Client presentation prep takes 2 days. Deadline is in 10 days.",
      "output": "Bottleneck analysis with specific fix recommendations to get back on schedule"
    }
  ],
  "checklist": [
    "Full process is mapped",
    "Bottleneck is correctly identified (not a symptom)",
    "Root cause is diagnosed",
    "Both short-term and long-term fixes are proposed",
    "Owner and timeline are assigned for each fix"
  ],
  "tools": ["document", "spreadsheet"],
  "agents": ["nova"],
  "pipelines": ["project-management"],
  "metadata": {
    "version": "1.0",
    "author": "agency",
    "tags": ["operations", "workflow", "project-management", "efficiency"],
    "lastUpdated": "2026-03-24"
  }
}
